<?xml version="1.0" encoding="utf-8" ?>
<dwsync>
<file name="image2.jpeg" server="C:/xamppok/htdocs/alfofinal/" local="119600064000000000" remote="119600064000000000" Dst="1" />
<file name="image3.jpeg" server="C:/xamppok/htdocs/alfofinal/" local="119600064000000000" remote="119600064000000000" Dst="1" />
<file name="image4.png" server="C:/xamppok/htdocs/alfofinal/" local="119600064000000000" remote="119600064000000000" Dst="1" />
<file name="image5.png" server="C:/xamppok/htdocs/alfofinal/" local="119600064000000000" remote="119600064000000000" Dst="1" />
<file name="image6.png" server="C:/xamppok/htdocs/alfofinal/" local="119600064000000000" remote="119600064000000000" Dst="1" />
<file name="sunglass hut instagram wall.html" server="C:/xamppok/htdocs/alfofinal/" local="130643828380754971" remote="130643828380000000" Dst="1" />
<file name="image2.jpeg" server="www.bug01.com//public_html/crystal-bits.co.uk/alfonso/" local="119600064000000000" remote="130651292400000000" Dst="1" />
<file name="image3.jpeg" server="www.bug01.com//public_html/crystal-bits.co.uk/alfonso/" local="119600064000000000" remote="130651292400000000" Dst="1" />
<file name="image4.png" server="www.bug01.com//public_html/crystal-bits.co.uk/alfonso/" local="119600064000000000" remote="130651292400000000" Dst="1" />
<file name="image5.png" server="www.bug01.com//public_html/crystal-bits.co.uk/alfonso/" local="119600064000000000" remote="130651292400000000" Dst="1" />
<file name="image6.png" server="www.bug01.com//public_html/crystal-bits.co.uk/alfonso/" local="119600064000000000" remote="130651292400000000" Dst="1" />
<file name="sunglass hut instagram wall.html" server="www.bug01.com//public_html/crystal-bits.co.uk/alfonso/" local="130643828380754971" remote="130651292400000000" Dst="1" />
</dwsync>